{
  "$schema": "https://mintlify.com/schema.json",
  "name": "Giselle Docs",
  "logo": {
    "dark": "/logo/dark.svg",
    "light": "/logo/light.svg"
  },
  "favicon": "/favicon.svg",
  "colors": {
    "primary": "#0D9373",
    "light": "#07C983",
    "dark": "#0D9373",
    "anchors": {
      "from": "#0D9373",
      "to": "#07C983"
    }
  },
  "topbarLinks": [
    {
      "name": "Support",
      "url": "mailto:support@giselles.ai"
    },
    {
      "name": "Log in",
      "url": "https://studio.giselles.ai/login"
    },
    {
      "name": "Sign up",
      "url": "https://studio.giselles.ai/signup"
    }
  ],
  "topbarCtaButton": {
    "name": "Get Started",
    "url": "https://studio.giselles.ai/"
  },
  "anchors": [
    {
      "name": "About Giselle",
      "icon": "house",
      "url": "https://giselles.ai"
    },
    {
      "name": "Documentation",
      "icon": "book-open-cover",
      "url": "https://docs.giselles.ai"
    },
    {
      "name": "Blog",
      "icon": "newspaper",
      "url": "https://giselles.ai/blog"
    }
  ],
  "navigation": [
    {
      "group": "Get Started",
      "pages": [
        "introduction",
        "quickstart",
        "development"
      ]
    },
    {
      "group": "Essentials",
      "pages": [
        "essentials/markdown",
        "essentials/code",
        "essentials/images",
        "essentials/settings",
        "essentials/navigation",
        "essentials/reusable-snippets"
      ]
    }
  ],
  "footerSocials": {
    "facebook": "https://www.facebook.com/GiselleAI",
    "x": "https://x.com/Giselles_AI",
    "youtube": "https://www.youtube.com/@Giselle_AI",
    "instagram": "https://www.instagram.com/giselle_de_ai/",
    "github": "https://github.com/giselles-ai/giselle"
  }
}
